{"nodes": [{"id": "apps_mobile_lib_features_wellness_widgets_sleep_card_dart", "label": "sleep_card.dart", "file_type": "code", "source_file": "apps\\mobile\\lib\\features\\wellness\\widgets\\sleep_card.dart", "source_location": null}, {"id": "apps_mobile_lib_features_wellness_widgets_sleep_card_dart_sleepcard", "label": "SleepCard", "file_type": "code", "source_file": "apps\\mobile\\lib\\features\\wellness\\widgets\\sleep_card.dart", "source_location": null}, {"id": "apps_mobile_lib_features_wellness_widgets_sleep_card_dart_sleepstagesbar", "label": "_SleepStagesBar", "file_type": "code", "source_file": "apps\\mobile\\lib\\features\\wellness\\widgets\\sleep_card.dart", "source_location": null}, {"id": "apps_mobile_lib_features_wellness_widgets_sleep_card_dart_stagelegend", "label": "_StageLegend", "file_type": "code", "source_file": "apps\\mobile\\lib\\features\\wellness\\widgets\\sleep_card.dart", "source_location": null}, {"id": "apps_mobile_lib_features_wellness_widgets_sleep_card_dart_sleeptrendchart", "label": "_SleepTrendChart", "file_type": "code", "source_file": "apps\\mobile\\lib\\features\\wellness\\widgets\\sleep_card.dart", "source_location": null}, {"id": "apps_mobile_lib_features_wellness_widgets_sleep_card_dart_scorebadge", "label": "_ScoreBadge", "file_type": "code", "source_file": "apps\\mobile\\lib\\features\\wellness\\widgets\\sleep_card.dart", "source_location": null}, {"id": "apps_mobile_lib_features_wellness_widgets_sleep_card_dart_build", "label": "build", "file_type": "code", "source_file": "apps\\mobile\\lib\\features\\wellness\\widgets\\sleep_card.dart", "source_location": null}, {"id": "apps_mobile_lib_features_wellness_widgets_sleep_card_dart_column", "label": "Column", "file_type": "code", "source_file": "apps\\mobile\\lib\\features\\wellness\\widgets\\sleep_card.dart", "source_location": null}, {"id": "apps_mobile_lib_features_wellness_widgets_sleep_card_dart_icon", "label": "Icon", "file_type": "code", "source_file": "apps\\mobile\\lib\\features\\wellness\\widgets\\sleep_card.dart", "source_location": null}, {"id": "apps_mobile_lib_features_wellness_widgets_sleep_card_dart_sizedbox", "label": "SizedBox", "file_type": "code", "source_file": "apps\\mobile\\lib\\features\\wellness\\widgets\\sleep_card.dart", "source_location": null}, {"id": "apps_mobile_lib_features_wellness_widgets_sleep_card_dart_row", "label": "Row", "file_type": "code", "source_file": "apps\\mobile\\lib\\features\\wellness\\widgets\\sleep_card.dart", "source_location": null}, {"id": "apps_mobile_lib_features_wellness_widgets_sleep_card_dart_center", "label": "Center", "file_type": "code", "source_file": "apps\\mobile\\lib\\features\\wellness\\widgets\\sleep_card.dart", "source_location": null}, {"id": "apps_mobile_lib_features_wellness_widgets_sleep_card_dart_barchart", "label": "BarChart", "file_type": "code", "source_file": "apps\\mobile\\lib\\features\\wellness\\widgets\\sleep_card.dart", "source_location": null}, {"id": "apps_mobile_lib_features_wellness_widgets_sleep_card_dart_barchartgroupdata", "label": "BarChartGroupData", "file_type": "code", "source_file": "apps\\mobile\\lib\\features\\wellness\\widgets\\sleep_card.dart", "source_location": null}, {"id": "apps_mobile_lib_features_wellness_widgets_sleep_card_dart_axistitles", "label": "AxisTitles", "file_type": "code", "source_file": "apps\\mobile\\lib\\features\\wellness\\widgets\\sleep_card.dart", "source_location": null}, {"id": "apps_mobile_lib_features_wellness_widgets_sleep_card_dart_sidetitlewidget", "label": "SideTitleWidget", "file_type": "code", "source_file": "apps\\mobile\\lib\\features\\wellness\\widgets\\sleep_card.dart", "source_location": null}, {"id": "apps_mobile_lib_features_wellness_widgets_sleep_card_dart_container", "label": "Container", "file_type": "code", "source_file": "apps\\mobile\\lib\\features\\wellness\\widgets\\sleep_card.dart", "source_location": null}, {"id": "dart_math", "label": "dart:math", "file_type": "code", "source_file": "apps\\mobile\\lib\\features\\wellness\\widgets\\sleep_card.dart", "source_location": null}, {"id": "package_fl_chart_fl_chart_dart", "label": "package:fl_chart/fl_chart.dart", "file_type": "code", "source_file": "apps\\mobile\\lib\\features\\wellness\\widgets\\sleep_card.dart", "source_location": null}, {"id": "package_flutter_material_dart", "label": "package:flutter/material.dart", "file_type": "code", "source_file": "apps\\mobile\\lib\\features\\wellness\\widgets\\sleep_card.dart", "source_location": null}, {"id": "core_services_health_service_dart", "label": "../../../core/services/health_service.dart", "file_type": "code", "source_file": "apps\\mobile\\lib\\features\\wellness\\widgets\\sleep_card.dart", "source_location": null}, {"id": "core_theme_app_colors_dart", "label": "../../../core/theme/app_colors.dart", "file_type": "code", "source_file": "apps\\mobile\\lib\\features\\wellness\\widgets\\sleep_card.dart", "source_location": null}, {"id": "core_theme_app_text_styles_dart", "label": "../../../core/theme/app_text_styles.dart", "file_type": "code", "source_file": "apps\\mobile\\lib\\features\\wellness\\widgets\\sleep_card.dart", "source_location": null}], "edges": [{"source": "apps_mobile_lib_features_wellness_widgets_sleep_card_dart", "target": "apps_mobile_lib_features_wellness_widgets_sleep_card_dart_sleepcard", "relation": "defines", "confidence": "EXTRACTED", "confidence_score": 1.0, "source_file": "apps\\mobile\\lib\\features\\wellness\\widgets\\sleep_card.dart", "source_location": null, "weight": 1.0}, {"source": "apps_mobile_lib_features_wellness_widgets_sleep_card_dart", "target": "apps_mobile_lib_features_wellness_widgets_sleep_card_dart_sleepstagesbar", "relation": "defines", "confidence": "EXTRACTED", "confidence_score": 1.0, "source_file": "apps\\mobile\\lib\\features\\wellness\\widgets\\sleep_card.dart", "source_location": null, "weight": 1.0}, {"source": "apps_mobile_lib_features_wellness_widgets_sleep_card_dart", "target": "apps_mobile_lib_features_wellness_widgets_sleep_card_dart_stagelegend", "relation": "defines", "confidence": "EXTRACTED", "confidence_score": 1.0, "source_file": "apps\\mobile\\lib\\features\\wellness\\widgets\\sleep_card.dart", "source_location": null, "weight": 1.0}, {"source": "apps_mobile_lib_features_wellness_widgets_sleep_card_dart", "target": "apps_mobile_lib_features_wellness_widgets_sleep_card_dart_sleeptrendchart", "relation": "defines", "confidence": "EXTRACTED", "confidence_score": 1.0, "source_file": "apps\\mobile\\lib\\features\\wellness\\widgets\\sleep_card.dart", "source_location": null, "weight": 1.0}, {"source": "apps_mobile_lib_features_wellness_widgets_sleep_card_dart", "target": "apps_mobile_lib_features_wellness_widgets_sleep_card_dart_scorebadge", "relation": "defines", "confidence": "EXTRACTED", "confidence_score": 1.0, "source_file": "apps\\mobile\\lib\\features\\wellness\\widgets\\sleep_card.dart", "source_location": null, "weight": 1.0}, {"source": "apps_mobile_lib_features_wellness_widgets_sleep_card_dart", "target": "apps_mobile_lib_features_wellness_widgets_sleep_card_dart_build", "relation": "defines", "confidence": "EXTRACTED", "confidence_score": 1.0, "source_file": "apps\\mobile\\lib\\features\\wellness\\widgets\\sleep_card.dart", "source_location": null, "weight": 1.0}, {"source": "apps_mobile_lib_features_wellness_widgets_sleep_card_dart", "target": "apps_mobile_lib_features_wellness_widgets_sleep_card_dart_column", "relation": "defines", "confidence": "EXTRACTED", "confidence_score": 1.0, "source_file": "apps\\mobile\\lib\\features\\wellness\\widgets\\sleep_card.dart", "source_location": null, "weight": 1.0}, {"source": "apps_mobile_lib_features_wellness_widgets_sleep_card_dart", "target": "apps_mobile_lib_features_wellness_widgets_sleep_card_dart_icon", "relation": "defines", "confidence": "EXTRACTED", "confidence_score": 1.0, "source_file": "apps\\mobile\\lib\\features\\wellness\\widgets\\sleep_card.dart", "source_location": null, "weight": 1.0}, {"source": "apps_mobile_lib_features_wellness_widgets_sleep_card_dart", "target": "apps_mobile_lib_features_wellness_widgets_sleep_card_dart_sizedbox", "relation": "defines", "confidence": "EXTRACTED", "confidence_score": 1.0, "source_file": "apps\\mobile\\lib\\features\\wellness\\widgets\\sleep_card.dart", "source_location": null, "weight": 1.0}, {"source": "apps_mobile_lib_features_wellness_widgets_sleep_card_dart", "target": "apps_mobile_lib_features_wellness_widgets_sleep_card_dart_row", "relation": "defines", "confidence": "EXTRACTED", "confidence_score": 1.0, "source_file": "apps\\mobile\\lib\\features\\wellness\\widgets\\sleep_card.dart", "source_location": null, "weight": 1.0}, {"source": "apps_mobile_lib_features_wellness_widgets_sleep_card_dart", "target": "apps_mobile_lib_features_wellness_widgets_sleep_card_dart_center", "relation": "defines", "confidence": "EXTRACTED", "confidence_score": 1.0, "source_file": "apps\\mobile\\lib\\features\\wellness\\widgets\\sleep_card.dart", "source_location": null, "weight": 1.0}, {"source": "apps_mobile_lib_features_wellness_widgets_sleep_card_dart", "target": "apps_mobile_lib_features_wellness_widgets_sleep_card_dart_barchart", "relation": "defines", "confidence": "EXTRACTED", "confidence_score": 1.0, "source_file": "apps\\mobile\\lib\\features\\wellness\\widgets\\sleep_card.dart", "source_location": null, "weight": 1.0}, {"source": "apps_mobile_lib_features_wellness_widgets_sleep_card_dart", "target": "apps_mobile_lib_features_wellness_widgets_sleep_card_dart_barchartgroupdata", "relation": "defines", "confidence": "EXTRACTED", "confidence_score": 1.0, "source_file": "apps\\mobile\\lib\\features\\wellness\\widgets\\sleep_card.dart", "source_location": null, "weight": 1.0}, {"source": "apps_mobile_lib_features_wellness_widgets_sleep_card_dart", "target": "apps_mobile_lib_features_wellness_widgets_sleep_card_dart_axistitles", "relation": "defines", "confidence": "EXTRACTED", "confidence_score": 1.0, "source_file": "apps\\mobile\\lib\\features\\wellness\\widgets\\sleep_card.dart", "source_location": null, "weight": 1.0}, {"source": "apps_mobile_lib_features_wellness_widgets_sleep_card_dart", "target": "apps_mobile_lib_features_wellness_widgets_sleep_card_dart_sidetitlewidget", "relation": "defines", "confidence": "EXTRACTED", "confidence_score": 1.0, "source_file": "apps\\mobile\\lib\\features\\wellness\\widgets\\sleep_card.dart", "source_location": null, "weight": 1.0}, {"source": "apps_mobile_lib_features_wellness_widgets_sleep_card_dart", "target": "apps_mobile_lib_features_wellness_widgets_sleep_card_dart_container", "relation": "defines", "confidence": "EXTRACTED", "confidence_score": 1.0, "source_file": "apps\\mobile\\lib\\features\\wellness\\widgets\\sleep_card.dart", "source_location": null, "weight": 1.0}, {"source": "apps_mobile_lib_features_wellness_widgets_sleep_card_dart", "target": "dart_math", "relation": "imports", "confidence": "EXTRACTED", "confidence_score": 1.0, "source_file": "apps\\mobile\\lib\\features\\wellness\\widgets\\sleep_card.dart", "source_location": null, "weight": 1.0}, {"source": "apps_mobile_lib_features_wellness_widgets_sleep_card_dart", "target": "package_fl_chart_fl_chart_dart", "relation": "imports", "confidence": "EXTRACTED", "confidence_score": 1.0, "source_file": "apps\\mobile\\lib\\features\\wellness\\widgets\\sleep_card.dart", "source_location": null, "weight": 1.0}, {"source": "apps_mobile_lib_features_wellness_widgets_sleep_card_dart", "target": "package_flutter_material_dart", "relation": "imports", "confidence": "EXTRACTED", "confidence_score": 1.0, "source_file": "apps\\mobile\\lib\\features\\wellness\\widgets\\sleep_card.dart", "source_location": null, "weight": 1.0}, {"source": "apps_mobile_lib_features_wellness_widgets_sleep_card_dart", "target": "core_services_health_service_dart", "relation": "imports", "confidence": "EXTRACTED", "confidence_score": 1.0, "source_file": "apps\\mobile\\lib\\features\\wellness\\widgets\\sleep_card.dart", "source_location": null, "weight": 1.0}, {"source": "apps_mobile_lib_features_wellness_widgets_sleep_card_dart", "target": "core_theme_app_colors_dart", "relation": "imports", "confidence": "EXTRACTED", "confidence_score": 1.0, "source_file": "apps\\mobile\\lib\\features\\wellness\\widgets\\sleep_card.dart", "source_location": null, "weight": 1.0}, {"source": "apps_mobile_lib_features_wellness_widgets_sleep_card_dart", "target": "core_theme_app_text_styles_dart", "relation": "imports", "confidence": "EXTRACTED", "confidence_score": 1.0, "source_file": "apps\\mobile\\lib\\features\\wellness\\widgets\\sleep_card.dart", "source_location": null, "weight": 1.0}]}